brian2/__init__.py
brian2/_version.py
brian2/conftest.py
brian2/hears.py
brian2/numpy_.py
brian2/only.py
brian2/codegen/__init__.py
brian2/codegen/_prefs.py
brian2/codegen/codeobject.py
brian2/codegen/cpp_prefs.py
brian2/codegen/get_cpu_flags.py
brian2/codegen/optimisation.py
brian2/codegen/permutation_analysis.py
brian2/codegen/statements.py
brian2/codegen/targets.py
brian2/codegen/templates.py
brian2/codegen/translation.py
brian2/codegen/generators/GSL_generator.py
brian2/codegen/generators/__init__.py
brian2/codegen/generators/base.py
brian2/codegen/generators/cpp_generator.py
brian2/codegen/generators/cython_generator.py
brian2/codegen/generators/numpy_generator.py
brian2/codegen/runtime/__init__.py
brian2/codegen/runtime/GSLcython_rt/GSLcython_rt.py
brian2/codegen/runtime/GSLcython_rt/__init__.py
brian2/codegen/runtime/GSLcython_rt/templates/stateupdate.pyx
brian2/codegen/runtime/cython_rt/__init__.py
brian2/codegen/runtime/cython_rt/cython_rt.py
brian2/codegen/runtime/cython_rt/extension_manager.py
brian2/codegen/runtime/cython_rt/templates/common_group.pyx
brian2/codegen/runtime/cython_rt/templates/group_get_indices.pyx
brian2/codegen/runtime/cython_rt/templates/group_variable_get.pyx
brian2/codegen/runtime/cython_rt/templates/group_variable_get_conditional.pyx
brian2/codegen/runtime/cython_rt/templates/group_variable_set.pyx
brian2/codegen/runtime/cython_rt/templates/group_variable_set_conditional.pyx
brian2/codegen/runtime/cython_rt/templates/ratemonitor.pyx
brian2/codegen/runtime/cython_rt/templates/reset.pyx
brian2/codegen/runtime/cython_rt/templates/spatialstateupdate.pyx
brian2/codegen/runtime/cython_rt/templates/spikegenerator.pyx
brian2/codegen/runtime/cython_rt/templates/spikemonitor.pyx
brian2/codegen/runtime/cython_rt/templates/statemonitor.pyx
brian2/codegen/runtime/cython_rt/templates/stateupdate.pyx
brian2/codegen/runtime/cython_rt/templates/summed_variable.pyx
brian2-2.10.1.dist-info/METADATA
brian2-2.10.1.dist-info/WHEEL
brian2-2.10.1.dist-info/top_level.txt
brian2-2.10.1.dist-info/RECORD
brian2-2.10.1.dist-info/licenses/AUTHORS
brian2-2.10.1.dist-info/licenses/CONTRIBUTORS
brian2-2.10.1.dist-info/licenses/LICENSE
