Metadata-Version: 2.4
Name: Brian2
Version: 2.10.1
Summary: A clock-driven simulator for spiking neural networks
Author: Marcel Stimberg, Dan Goodman, Benjamin Evans, Romain Brette
License-Expression: CECILL-2.1
Project-URL: Homepage, https://briansimulator.org
Project-URL: Documentation, https://brian2.readthedocs.io/
Project-URL: Source, https://github.com/brian-team/brian2
Project-URL: Tracker, https://github.com/brian-team/brian2/issues
Keywords: computational neuroscience,simulation,neural networks,spiking neurons,biological neural networks,research
Classifier: Development Status :: 5 - Production/Stable
Classifier: Intended Audience :: Science/Research
Classifier: Natural Language :: English
Classifier: Operating System :: OS Independent
Classifier: Programming Language :: Python
Classifier: Programming Language :: Python :: 3
Classifier: Topic :: Scientific/Engineering :: Bio-Informatics
Requires-Python: >=3.12
License-File: LICENSE
License-File: AUTHORS
License-File: CONTRIBUTORS
Requires-Dist: numpy>=2.0.0
Requires-Dist: cython<3.1.4,>=0.29.21
Requires-Dist: sympy>=1.2
Requires-Dist: pyparsing!=3.2.4,>=3
Requires-Dist: jinja2>=2.7
Requires-Dist: py-cpuinfo; platform_system == "Windows"
Requires-Dist: setuptools>=61
Requires-Dist: packaging
Provides-Extra: test
Requires-Dist: pytest>=8; extra == "test"
Requires-Dist: pytest-xdist>=1.22.3; extra == "test"
Requires-Dist: pytest-cov>=2.0; extra == "test"
Requires-Dist: pytest-timeout; extra == "test"
Provides-Extra: docs
Requires-Dist: sphinx>=7; extra == "docs"
Requires-Dist: ipython>=5; extra == "docs"
Requires-Dist: sphinx-tabs; extra == "docs"
Dynamic: license-file
